iam_ape/__init__.py
iam_ape/aws_iam_actions/__init__.py
iam_ape/aws_iam_actions/aws_iam_actions.tar.gz
iam_ape/aws_iam_actions/scrape_iam_actions.py
iam_ape/consts.py
iam_ape/evaluator.py
iam_ape/exceptions.py
iam_ape/expand_policy.py
iam_ape/helper_classes.py
iam_ape/helper_functions.py
iam_ape/helper_types.py
iam_ape/main.py
iam_ape/py.typed
iam_ape-1.1.6.dist-info/LICENSE
iam_ape-1.1.6.dist-info/METADATA
iam_ape-1.1.6.dist-info/WHEEL
iam_ape-1.1.6.dist-info/entry_points.txt
iam_ape-1.1.6.dist-info/RECORD
