Metadata-Version: 2.1
Name: iam-ape
Version: 1.1.6
Summary: IAM AWS Permissions Evaluator
Home-page: https://github.com/orcasecurity/orca-toolbox/raw/main/iam-ape/
License: GPL-3.0-or-later
Keywords: aws,iam
Author: Tohar Braun, Orca Security
Author-email: tohar@orca.security
Requires-Python: >=3.8,<4.0
Classifier: Development Status :: 5 - Production/Stable
Classifier: Intended Audience :: Developers
Classifier: Intended Audience :: System Administrators
Classifier: License :: OSI Approved :: GNU General Public License v3 (GPLv3)
Classifier: License :: OSI Approved :: GNU General Public License v3 or later (GPLv3+)
Classifier: Programming Language :: Python :: 3
Classifier: Programming Language :: Python :: 3.8
Classifier: Programming Language :: Python :: 3.9
Classifier: Programming Language :: Python :: 3.10
Classifier: Programming Language :: Python :: 3.11
Classifier: Programming Language :: Python :: 3.12
Classifier: Programming Language :: Python :: 3.13
Classifier: Topic :: Security
Requires-Dist: beautifulsoup4 (>=4.8.2,<5.0.0)
Requires-Dist: boto3 (>=1.24.0,<2.0.0)
Requires-Dist: requests (>=2.27.1,<3.0.0)
Requires-Dist: tqdm (>=4.63.0,<5.0.0)
Project-URL: Repository, https://github.com/orcasecurity/orca-toolbox/raw/main/iam-ape/
